dundle.py
dundle-2025.6.5.dist-info/METADATA
dundle-2025.6.5.dist-info/WHEEL
dundle-2025.6.5.dist-info/top_level.txt
dundle-2025.6.5.dist-info/RECORD
